{
  "type": "FeatureCollection",
  "features": [
    {
      "type": "Feature",
      "id": "feature_af8fe9e119864f728e59f45839a5d485",
      "properties": {
        "class": "unsafe",
        "id": "feature_af8fe9e119864f728e59f45839a5d485",
        "confidence": 1.0,
        "category": "navigation",
        "source": "ground station",
        "altitude_m": 81.45348,
        "marker-color": "#159ffb",
        "fill": "#159ffb",
        "fill-opacity": 0.25
      },
      "geometry": {
        "type": "Polygon",
        "coordinates": [
          [
            [
              23.708138927440658,
              37.96171051135898,
              81.45348704978824
            ],
            [
              23.708543204244187,
              37.96136425579535,
              77.9050143873319
            ],
            [
              23.70810167323846,
              37.9610685895752,
              80.45509588345885
            ],
            [
              23.70769897760545,
              37.96140831450947,
              79.79395764693618
            ],
            [
              23.708138927440658,
              37.96171051135898,
              81.45348704978824
            ],
            [
              23.708138927440658,
              37.96171051135898,
              81.45348704978824
            ]
          ]
        ]
      }
    },
    {
      "type": "Feature",
      "id": "feature_75776ecb8e724fce84b82692b81386f4",
      "properties": {
        "class": "unsafe",
        "id": "feature_75776ecb8e724fce84b82692b81386f4",
        "confidence": 1.0,
        "category": "navigation",
        "source": "ground station",
        "altitude_m": 80.81625,
        "marker-color": "#ff0000",
        "fill": "#ff0000",
        "fill-opacity": 0.25
      },
      "geometry": {
        "type": "Polygon",
        "coordinates": [
          [
            [
              23.709904603315827,
              37.96123001935733,
              80.81625712290406
            ],
            [
              23.710569273292936,
              37.96074013770297,
              88.15715405531228
            ],
            [
              23.709615637784378,
              37.960064451750554,
              93.20869940984994
            ],
            [
              23.7089827138966,
              37.960601611738554,
              80.87563210166991
            ],
            [
              23.709904602886436,
              37.96123001948048,
              80.8162629166618
            ],
            [
              23.709904603315827,
              37.96123001935733,
              80.81625712290406
            ]
          ]
        ]
      }
    },
    {
      "type": "Feature",
      "id": "feature_c3a67c1229814bc29269d83927c3f340",
      "properties": {
        "class": "road",
        "id": "feature_c3a67c1229814bc29269d83927c3f340",
        "confidence": 1.0,
        "category": "navigation",
        "source": "ground station",
        "altitude_m": 81.41095,
        "marker-color": "#ffeb04"
      },
      "geometry": {
        "type": "LineString",
        "coordinates": [
          [
            23.707572795965827,
            37.9597975237309,
            75.00992710515857
          ],
          [
            23.708426918280562,
            37.96040005457287,
            79.18136891815811
          ],
          [
            23.70930370547713,
            37.96099696167382,
            80.9818926891312
          ],
          [
            23.71026275521201,
            37.961654142203045,
            80.40669077076018
          ],
          [
            23.711298968212077,
            37.96214218194797,
            81.41094846464694
          ]
        ]
      }
    },
    {
      "type": "Feature",
      "id": "feature_6ce38fdd4b5a4872a5e9e8101bd2d7fa",
      "properties": {
        "class": "citizen",
        "id": "feature_6ce38fdd4b5a4872a5e9e8101bd2d7fa",
        "confidence": 1.0,
        "category": "citizen",
        "source": "ground station",
        "altitude_m": 90.599205,
        "marker-color": "#ff0000"
      },
      "geometry": {
        "type": "Point",
        "coordinates": [
          23.708027799876476,
          37.96083978974138,
          90.5992048708722
        ]
      }
    },
    {
      "type": "Feature",
      "id": "feature_fc213fe87abb40b184a62b4ff0b36046",
      "properties": {
        "class": "animal",
        "id": "feature_fc213fe87abb40b184a62b4ff0b36046",
        "confidence": 1.0,
        "category": "animal",
        "source": "ground station",
        "altitude_m": 83.39161,
        "marker-color": "#ff0000"
      },
      "geometry": {
        "type": "Point",
        "coordinates": [
          23.708587728472654,
          37.9618036947925,
          83.39160542935133
        ]
      }
    },
    {
      "type": "Feature",
      "id": "feature_d2a12b79fbd64b5c96f4680ba4c7b165",
      "properties": {
        "class": "barrier",
        "id": "feature_d2a12b79fbd64b5c96f4680ba4c7b165",
        "confidence": 1.0,
        "category": "barrier",
        "source": "ground station",
        "altitude_m": 81.5660553,
        "marker-color": "#ff0000"
      },
      "geometry": {
        "type": "Point",
        "coordinates": [
          23.70866561365793,
          37.96091799273489,
          81.56605793442577
        ]
      }
    },
    {
      "type": "Feature",
      "id": "feature_f8d6136576f447198644d93680a717e2",
      "properties": {
        "class": "debris",
        "id": "feature_f8d6136576f447198644d93680a717e2",
        "confidence": 1.0,
        "category": "debris",
        "source": "ground station",
        "altitude_m": 91.27954,
        "marker-color": "#ff0000"
      },
      "geometry": {
        "type": "Point",
        "coordinates": [
          23.70968763233334,
          37.962216007392065,
          91.27954086009413
        ]
      }
    },
    {
      "type": "Feature",
      "id": "feature_eaa76edc920f40e59df6a5d703688c43",
      "properties": {
        "class": "unsafe",
        "id": "feature_eaa76edc920f40e59df6a5d703688c43",
        "confidence": 1.0,
        "category": "navigation",
        "source": "ground station",
        "altitude_m": 81.21531,
        "marker-color": "#cf0fc0",
        "fill": "#cf0fc0",
        "fill-opacity": 0.25
      },
      "geometry": {
        "type": "Polygon",
        "coordinates": [
          [
            [
              23.707214426759997,
              37.96224842301577,
              81.2153070922941
            ],
            [
              23.707711601122337,
              37.96176572135124,
              80.07752534095198
            ],
            [
              23.706823068700334,
              37.96109575842559,
              79.92868645302951
            ],
            [
              23.70619019916441,
              37.96158385350073,
              97.74648581072688
            ],
            [
              23.707214426759997,
              37.96224842301577,
              81.2153070922941
            ]
          ]
        ]
      }
    }
  ],
  "observer_status": {
    "last_update": "2026-06-22 16:09:23",
    "fe_updated": 0,
    "mobile_updated": 0,
    "ar_updated": 1
  },
  "mqtt_latest": {
    "message": {
      "header": {
        "stamp": {
          "sec": 1782133870,
          "nanosec": 533275842
        },
        "frame_id": "b2/base_link"
      },
      "roll": 0.0,
      "pitch": 0.0,
      "yaw": 0.0,
      "latitude": 37.96205989167726,
      "longitude": 23.711789295677,
      "battery_temperature": 0,
      "power_voltage": 0,
      "power_current": 0,
      "temperature_ntc1": 0,
      "temperature_ntc2": 0,
      "mode": 0,
      "commander": "none",
      "behavior": "IDLE",
      "action_command": "{}"
    },
    "topic": "/b2/ugv_status_from_ros2",
    "time": "2026-06-22 16:11:10",
    "motion": {
      "enabled": true,
      "start_after_sec": 5.0,
      "start_at_epoch": 1782127570.4916441,
      "interval_sec": 1.0,
      "lat_step": 1e-05,
      "lon_step": 2e-05,
      "yaw_step": 0.0,
      "last_step_epoch": 1782133870.5332758
    }
  }
}